LICENSE
MANIFEST.in
README.md
setup.py
sub_finder_vvvin.egg-info/PKG-INFO
sub_finder_vvvin.egg-info/SOURCES.txt
sub_finder_vvvin.egg-info/dependency_links.txt
sub_finder_vvvin.egg-info/requires.txt
sub_finder_vvvin.egg-info/top_level.txt
subfinder/__init__.py
subfinder/suburbgeo.dat
subfinder/suburbs.dat
subfinder/__pycache__/subfinder.cpython-38.pyc
subfinder_vvvin.egg-info/PKG-INFO
subfinder_vvvin.egg-info/SOURCES.txt
subfinder_vvvin.egg-info/dependency_links.txt
subfinder_vvvin.egg-info/requires.txt
subfinder_vvvin.egg-info/top_level.txt