Metadata-Version: 2.1
Name: subfinder-vvvin
Version: 1.1.3
Summary: A Address Finder
Author: mian
Author-email: wukuizongvincent@gmail.com
License: UNKNOWN
Platform: UNKNOWN
Classifier: Programming Language :: Python :: 3
Classifier: License :: OSI Approved :: MIT License
Classifier: Operating System :: OS Independent
License-File: LICENSE
